odoo/addons/web_widget_x2many_2d_matrix/README.rst
odoo/addons/web_widget_x2many_2d_matrix/__init__.py
odoo/addons/web_widget_x2many_2d_matrix/__manifest__.py
odoo/addons/web_widget_x2many_2d_matrix/i18n/ar.po
odoo/addons/web_widget_x2many_2d_matrix/i18n/de.po
odoo/addons/web_widget_x2many_2d_matrix/i18n/es.po
odoo/addons/web_widget_x2many_2d_matrix/i18n/fi.po
odoo/addons/web_widget_x2many_2d_matrix/i18n/fr.po
odoo/addons/web_widget_x2many_2d_matrix/i18n/hr.po
odoo/addons/web_widget_x2many_2d_matrix/i18n/it.po
odoo/addons/web_widget_x2many_2d_matrix/i18n/lt.po
odoo/addons/web_widget_x2many_2d_matrix/i18n/nl_NL.po
odoo/addons/web_widget_x2many_2d_matrix/i18n/pt_BR.po
odoo/addons/web_widget_x2many_2d_matrix/i18n/sl.po
odoo/addons/web_widget_x2many_2d_matrix/i18n/tr.po
odoo/addons/web_widget_x2many_2d_matrix/i18n/web_widget_x2many_2d_matrix.pot
odoo/addons/web_widget_x2many_2d_matrix/static/description/icon.png
odoo/addons/web_widget_x2many_2d_matrix/static/description/screenshot.png
odoo/addons/web_widget_x2many_2d_matrix/static/src/css/web_widget_x2many_2d_matrix.css
odoo/addons/web_widget_x2many_2d_matrix/static/src/js/2d_matrix_renderer.js
odoo/addons/web_widget_x2many_2d_matrix/static/src/js/abstract_view_matrix_limit_extend.js
odoo/addons/web_widget_x2many_2d_matrix/static/src/js/widget_x2many_2d_matrix.js
odoo/addons/web_widget_x2many_2d_matrix/views/assets.xml
odoo11_addon_web_widget_x2many_2d_matrix-11.0.1.1.2.dist-info/METADATA
odoo11_addon_web_widget_x2many_2d_matrix-11.0.1.1.2.dist-info/RECORD
odoo11_addon_web_widget_x2many_2d_matrix-11.0.1.1.2.dist-info/WHEEL
odoo11_addon_web_widget_x2many_2d_matrix-11.0.1.1.2.dist-info/top_level.txt
