Metadata-Version: 2.1
Name: odoo11-addon-web-widget-x2many-2d-matrix
Version: 11.0.1.1.2
Summary: Show list fields as a matrix
Home-page: https://github.com/OCA/web
Author: Therp BV, Tecnativa, Camptocamp, Odoo Community Association (OCA)
Author-email: support@odoo-community.org
License: AGPL-3
Platform: UNKNOWN
Classifier: Programming Language :: Python
Classifier: Framework :: Odoo
Classifier: License :: OSI Approved :: GNU Affero General Public License v3
Requires-Python: >=2.7, !=3.0.*, !=3.1.*, !=3.2.*, !=3.3.*, !=3.4.*
Requires-Dist: odoo (<11.1dev,>=11.0a)
